target_permutation_importances/__init__.py
target_permutation_importances/functional.py
target_permutation_importances/sklearn_wrapper.py
target_permutation_importances/typing.py
target_permutation_importances-2.1.0.dist-info/LICENSE
target_permutation_importances-2.1.0.dist-info/METADATA
target_permutation_importances-2.1.0.dist-info/WHEEL
target_permutation_importances-2.1.0.dist-info/RECORD
