Metadata-Version: 2.1
Name: target-permutation-importances
Version: 2.1.0
Summary: Compute (Target) Permutation Importances of a machine learning model
Home-page: https://github.com/kingychiu/target-permutation-importances
Author: Anthony Chiu
Author-email: kingychiu@gmail.com
Maintainer: Anthony Chiu
Maintainer-email: kingychiu@gmail.com
Requires-Python: >=3.9,<4.0
Classifier: Intended Audience :: Developers
Classifier: Intended Audience :: Science/Research
Classifier: Operating System :: MacOS
Classifier: Operating System :: Microsoft :: Windows
Classifier: Operating System :: POSIX
Classifier: Operating System :: Unix
Classifier: Programming Language :: Python :: 3
Classifier: Programming Language :: Python :: 3.9
Classifier: Programming Language :: Python :: 3.10
Classifier: Programming Language :: Python :: 3.11
Classifier: Programming Language :: Python :: 3.12
Classifier: Topic :: Scientific/Engineering
Classifier: Topic :: Scientific/Engineering :: Artificial Intelligence
Requires-Dist: beartype (>=0.14.1,<0.15.0)
Requires-Dist: numpy (>=1.23.5,<2.0.0)
Requires-Dist: pandas (>=2.0.3,<3.0.0)
Requires-Dist: scipy (>=1.9,<2.0)
Requires-Dist: tqdm (>=4.48.2,<5.0.0)
Project-URL: Documentation, https://target-permutation-importances.readthedocs.io/en/latest/
Project-URL: Repository, https://github.com/kingychiu/target-permutation-importances
